OSRSBytes/Hiscores.py
OSRSBytes/Items.py
OSRSBytes/Utilities.py
OSRSBytes/__init__.py
OSRSBytes/modules/fletching.json
OSRSBytes/modules/smithing.json
OSRSBytes/tests/__init__.py
OSRSBytes/tests/hiscores_test.py
OSRSBytes/tests/items_test.py
OSRSBytes_Dev-1.3.2.dist-info/LICENSE
OSRSBytes_Dev-1.3.2.dist-info/METADATA
OSRSBytes_Dev-1.3.2.dist-info/WHEEL
OSRSBytes_Dev-1.3.2.dist-info/top_level.txt
OSRSBytes_Dev-1.3.2.dist-info/RECORD
