Metadata-Version: 2.1
Name: OSRSBytes-Dev
Version: 1.3.2
Summary: An all-in-one OSRS Library with Hiscores and Grand Exchange Market Information
Home-page: https://github.com/Coffee-fueled-deadlines/OSRSBytes
Author: Coffee Fueled Deadlines
Author-email: cookm0803@gmail.com
License: UNKNOWN
Platform: UNKNOWN
Classifier: Programming Language :: Python :: 3
Classifier: License :: OSI Approved :: Eclipse Public License 2.0 (EPL-2.0)
Classifier: Operating System :: OS Independent
